{
  "id": "clefable",
  "nid": "0036",
  "dexNum": 36,
  "region": "kanto",
  "gen": 1,
  "type1": "fairy",
  "color": "pink",
  "ability1": "cutecharm",
  "ability2": "magicguard",
  "abilityHidden": "unaware",
  "isPrerelease": false,
  "isDefault": true,
  "isForm": false,
  "isLegendary": false,
  "isMythical": false,
  "isBaby": false,
  "isUltraBeast": false,
  "isParadox": false,
  "paradoxSpecies": [],
  "isConvergent": false,
  "convergentSpecies": [],
  "isCosmeticForm": false,
  "isFemaleForm": false,
  "hasGenderDifferences": false,
  "isBattleOnlyForm": false,
  "isFusion": false,
  "isMega": false,
  "isPrimal": false,
  "isGmax": false,
  "isRegional": false,
  "canGmax": false,
  "canDynamax": true,
  "canBeAlpha": true,
  "debutIn": "rb",
  "obtainableIn": [
    "rb-r",
    "rb-b",
    "y",
    "gs-g",
    "gs-s",
    "c",
    "frlg-fr",
    "frlg-lg",
    "dp-d",
    "dp-p",
    "pt",
    "hgss-hg",
    "hgss-ss",
    "b2w2-b2",
    "b2w2-w2",
    "go",
    "sm-s",
    "sm-m",
    "usum-us",
    "usum-um",
    "lgpe-lgp",
    "lgpe-lge",
    "swsh-sw",
    "swsh-sh",
    "bdsp-bd",
    "bdsp-sp",
    "la",
    "sv-s",
    "sv-v",
    "lza"
  ],
  "eventOnlyIn": [],
  "storableIn": [
    "rb-r",
    "rb-b",
    "y",
    "gs-g",
    "gs-s",
    "c",
    "rs-r",
    "rs-s",
    "frlg-fr",
    "frlg-lg",
    "e",
    "dp-d",
    "dp-p",
    "pt",
    "hgss-hg",
    "hgss-ss",
    "bw-b",
    "bw-w",
    "b2w2-b2",
    "b2w2-w2",
    "xy-x",
    "xy-y",
    "oras-or",
    "oras-as",
    "go",
    "sm-s",
    "sm-m",
    "usum-us",
    "usum-um",
    "lgpe-lgp",
    "lgpe-lge",
    "swsh-sw",
    "swsh-sh",
    "home",
    "bdsp-bd",
    "bdsp-sp",
    "la",
    "sv-s",
    "sv-v"
  ],
  "shinyReleased": true,
  "baseHp": 95,
  "baseAtk": 70,
  "baseDef": 73,
  "baseSpAtk": 95,
  "baseSpDef": 90,
  "baseSpeed": 60,
  "height": 130,
  "weight": 4000,
  "maleRate": 25,
  "femaleRate": 75,
  "baseForms": [],
  "forms": ["clefable-mega"],
  "refs": {
    "pkApiId": "36",
    "pkApiFormId": "36",
    "pkApiFormSlug": "clefable",
    "smogon": "clefable",
    "showdown": "clefable",
    "showdownName": "Clefable",
    "serebii": "clefable",
    "bulbapedia": "Clefable"
  },
  "evolvesFrom": "clefairy",
  "evoFromItem": "moonstone",
  "names": {
    "eng": "Clefable",
    "fra": "Mélodelfe",
    "deu": "Pixi",
    "jap": "ピクシー",
    "kor": "픽시",
    "chs": "皮可西",
    "cht": "皮可西"
  },
  "genus": {
    "eng": "Fairy Pokémon",
    "esp": "Pokémon Hada",
    "fra": "Pokémon Fée",
    "deu": "Feen-Pokémon",
    "ita": "Pokémon Fata",
    "jap": "ようせいポケモン",
    "kor": "요정포켓몬",
    "chs": "妖精宝可梦",
    "cht": "妖精寶可夢"
  },
  "speciesNames": {},
  "formNames": {}
}
