{
  "id": "cramorant-gulping",
  "nid": "0845-gulping",
  "dexNum": 845,
  "formId": "gulping",
  "region": "galar",
  "gen": 8,
  "type1": "flying",
  "type2": "water",
  "color": "blue",
  "ability1": "gulpmissile",
  "isPrerelease": false,
  "isDefault": false,
  "isForm": true,
  "isLegendary": false,
  "isMythical": false,
  "isBaby": false,
  "isUltraBeast": false,
  "isParadox": false,
  "paradoxSpecies": [],
  "isConvergent": false,
  "convergentSpecies": [],
  "isCosmeticForm": false,
  "isFemaleForm": false,
  "hasGenderDifferences": false,
  "isBattleOnlyForm": true,
  "isFusion": false,
  "isMega": false,
  "isPrimal": false,
  "isGmax": false,
  "isRegional": false,
  "canGmax": false,
  "canDynamax": true,
  "canBeAlpha": false,
  "debutIn": "swsh",
  "obtainableIn": ["swsh-sw", "swsh-sh", "sv-s", "sv-v"],
  "eventOnlyIn": [],
  "storableIn": [],
  "shinyReleased": true,
  "baseHp": 70,
  "baseAtk": 85,
  "baseDef": 55,
  "baseSpAtk": 85,
  "baseSpDef": 95,
  "baseSpeed": 85,
  "height": 80,
  "weight": 1800,
  "maleRate": 50,
  "femaleRate": 50,
  "baseSpecies": "cramorant",
  "baseForms": ["cramorant"],
  "forms": [],
  "refs": {
    "pkApiId": "10182",
    "pkApiFormId": "10341",
    "pkApiFormSlug": "cramorant-gulping",
    "smogon": "cramorant-gulping",
    "showdown": "cramorantgulping",
    "showdownName": "Cramorant-Gulping",
    "serebii": "cramorant",
    "bulbapedia": "Cramorant"
  },
  "names": {
    "eng": "Cramorant (Gulping Form)",
    "esp": "Cramorant (Forma Tragatodo)",
    "fra": "Nigosier (Forme Gobe-Tout)",
    "deu": "Urgl (Schlingform)",
    "ita": "Cramorant (Forma Inghiottitutto)",
    "jap": "ウッウ (うのみのすがた)",
    "kor": "윽우지 (그대로 삼킨 모습)",
    "chs": "古月鸟 (一口吞的样子)",
    "cht": "古月鳥 (一口吞的樣子)"
  },
  "genus": {
    "eng": "Gulp Pokémon",
    "esp": "Pokémon Tragón",
    "fra": "Pokémon Avaltouron",
    "deu": "Schling-Pokémon",
    "ita": "Pokémon Inghiottone",
    "jap": "うのみポケモン",
    "kor": "그대로삼키기포켓몬",
    "chs": "一口吞宝可梦",
    "cht": "一口吞寶可夢"
  },
  "speciesNames": {
    "eng": "Cramorant",
    "fra": "Nigosier",
    "deu": "Urgl",
    "jap": "ウッウ",
    "kor": "윽우지",
    "chs": "古月鸟",
    "cht": "古月鳥"
  },
  "formNames": {
    "eng": "Gulping Form",
    "esp": "Forma Tragatodo",
    "fra": "Forme Gobe-Tout",
    "deu": "Schlingform",
    "ita": "Forma Inghiottitutto",
    "jap": "うのみのすがた",
    "kor": "그대로 삼킨 모습",
    "chs": "一口吞的样子",
    "cht": "一口吞的樣子"
  }
}
