{
  "id": "garchomp-mega-z",
  "nid": "0445-mega-z",
  "dexNum": 445,
  "formId": "mega-z",
  "region": "kalos",
  "gen": 9,
  "type1": "dragon",
  "color": "blue",
  "ability1": "sandveil",
  "abilityHidden": "roughskin",
  "isPrerelease": false,
  "isDefault": false,
  "isForm": true,
  "isLegendary": false,
  "isMythical": false,
  "isBaby": false,
  "isUltraBeast": false,
  "isParadox": false,
  "paradoxSpecies": [],
  "isConvergent": false,
  "convergentSpecies": [],
  "isCosmeticForm": false,
  "isFemaleForm": false,
  "hasGenderDifferences": false,
  "isBattleOnlyForm": true,
  "isFusion": false,
  "isMega": true,
  "isPrimal": false,
  "isGmax": false,
  "isRegional": false,
  "canGmax": false,
  "canDynamax": false,
  "canBeAlpha": false,
  "debutIn": "lza",
  "obtainableIn": ["lza"],
  "eventOnlyIn": [],
  "storableIn": [],
  "shinyReleased": true,
  "baseHp": 108,
  "baseAtk": 130,
  "baseDef": 85,
  "baseSpAtk": 141,
  "baseSpDef": 85,
  "baseSpeed": 151,
  "height": 190,
  "weight": 9900,
  "maleRate": 50,
  "femaleRate": 50,
  "baseSpecies": "garchomp",
  "baseForms": [],
  "forms": [],
  "refs": {
    "pkApiId": "445",
    "pkApiFormId": "445",
    "pkApiFormSlug": "garchomp-mega-z",
    "smogon": "garchomp-mega-z",
    "showdown": "garchompmegaz",
    "showdownName": "Garchomp-Mega-Z",
    "serebii": "garchomp",
    "bulbapedia": "Garchomp"
  },
  "names": {
    "eng": "Mega Garchomp Z",
    "esp": "Mega Garchomp Z",
    "esla": "Mega Garchomp Z",
    "fra": "MégaCarchacrok Z",
    "deu": "Mega-Knakrack Z",
    "ita": "Mega Garchomp Z",
    "jap": "メガガブリアスZ",
    "kor": "메가한카리아스Z",
    "chs": "超级烈咬陆鲨Z",
    "cht": "超級烈咬陸鯊Z"
  },
  "genus": {
    "eng": "Mach Pokémon",
    "esp": "Pokémon Mach",
    "fra": "Pokémon Supersonic",
    "deu": "Rasanz-Pokémon",
    "ita": "Pokémon Mach",
    "jap": "マッハポケモン",
    "kor": "마하포켓몬",
    "chs": "音速宝可梦",
    "cht": "音速寶可夢"
  },
  "speciesNames": {
    "eng": "Garchomp",
    "fra": "Carchacrok",
    "deu": "Knakrack",
    "jap": "ガブリアス",
    "kor": "한카리아스",
    "chs": "烈咬陆鲨",
    "cht": "烈咬陸鯊"
  },
  "formNames": {
    "eng": "Mega Form Z",
    "esp": "Forma Mega Z",
    "esla": "Forma Mega Z",
    "fra": "Méga-Forme Z",
    "deu": "Mega-Form Z",
    "ita": "Forma Mega Z",
    "jap": "メガZ",
    "kor": "메가Z",
    "chs": "超级Z",
    "cht": "超級Z"
  }
}
