{
  "id": "garchomp",
  "nid": "0445",
  "dexNum": 445,
  "region": "sinnoh",
  "gen": 4,
  "type1": "dragon",
  "type2": "ground",
  "color": "blue",
  "ability1": "sandveil",
  "abilityHidden": "roughskin",
  "isPrerelease": false,
  "isDefault": true,
  "isForm": false,
  "isLegendary": false,
  "isMythical": false,
  "isBaby": false,
  "isUltraBeast": false,
  "isParadox": false,
  "paradoxSpecies": [],
  "isConvergent": false,
  "convergentSpecies": [],
  "isCosmeticForm": false,
  "isFemaleForm": false,
  "hasGenderDifferences": true,
  "isBattleOnlyForm": false,
  "isFusion": false,
  "isMega": false,
  "isPrimal": false,
  "isGmax": false,
  "isRegional": false,
  "canGmax": false,
  "canDynamax": true,
  "canBeAlpha": true,
  "debutIn": "dp",
  "obtainableIn": [
    "dp-d",
    "dp-p",
    "pt",
    "xy-x",
    "xy-y",
    "go",
    "sm-s",
    "sm-m",
    "usum-us",
    "usum-um",
    "swsh-sw",
    "swsh-sh",
    "bdsp-bd",
    "bdsp-sp",
    "la",
    "sv-s",
    "sv-v",
    "lza"
  ],
  "eventOnlyIn": [],
  "storableIn": [
    "dp-d",
    "dp-p",
    "pt",
    "hgss-hg",
    "hgss-ss",
    "bw-b",
    "bw-w",
    "b2w2-b2",
    "b2w2-w2",
    "xy-x",
    "xy-y",
    "oras-or",
    "oras-as",
    "go",
    "sm-s",
    "sm-m",
    "usum-us",
    "usum-um",
    "swsh-sw",
    "swsh-sh",
    "home",
    "bdsp-bd",
    "bdsp-sp",
    "la",
    "sv-s",
    "sv-v"
  ],
  "shinyReleased": true,
  "baseHp": 108,
  "baseAtk": 130,
  "baseDef": 95,
  "baseSpAtk": 80,
  "baseSpDef": 85,
  "baseSpeed": 102,
  "height": 190,
  "weight": 9500,
  "maleRate": 50,
  "femaleRate": 50,
  "baseForms": [],
  "forms": ["garchomp-f", "garchomp-mega", "garchomp-mega-z"],
  "refs": {
    "pkApiId": "445",
    "pkApiFormId": "445",
    "pkApiFormSlug": "garchomp",
    "smogon": "garchomp",
    "showdown": "garchomp",
    "showdownName": "Garchomp",
    "serebii": "garchomp",
    "bulbapedia": "Garchomp"
  },
  "evolvesFrom": "gabite",
  "evoFromLevel": 48,
  "names": {
    "eng": "Garchomp",
    "fra": "Carchacrok",
    "deu": "Knakrack",
    "jap": "ガブリアス",
    "kor": "한카리아스",
    "chs": "烈咬陆鲨",
    "cht": "烈咬陸鯊"
  },
  "genus": {
    "eng": "Mach Pokémon",
    "esp": "Pokémon Mach",
    "fra": "Pokémon Supersonic",
    "deu": "Rasanz-Pokémon",
    "ita": "Pokémon Mach",
    "jap": "マッハポケモン",
    "kor": "마하포켓몬",
    "chs": "音速宝可梦",
    "cht": "音速寶可夢"
  },
  "speciesNames": {},
  "formNames": {
    "eng": "Male",
    "esp": "Macho",
    "esla": "Macho",
    "fra": "Mâle",
    "deu": "Männlich",
    "ita": "Maschio",
    "jap": "オス",
    "kor": "수컷",
    "chs": "雄性",
    "cht": "雄性"
  }
}
