{
  "id": "glimmet",
  "nid": "0969",
  "dexNum": 969,
  "region": "paldea",
  "gen": 9,
  "type1": "rock",
  "type2": "poison",
  "color": "blue",
  "ability1": "toxicdebris",
  "abilityHidden": "corrosion",
  "isPrerelease": false,
  "isDefault": true,
  "isForm": false,
  "isLegendary": false,
  "isMythical": false,
  "isBaby": false,
  "isUltraBeast": false,
  "isParadox": false,
  "paradoxSpecies": [],
  "isConvergent": false,
  "convergentSpecies": [],
  "isCosmeticForm": false,
  "isFemaleForm": false,
  "hasGenderDifferences": false,
  "isBattleOnlyForm": false,
  "isFusion": false,
  "isMega": false,
  "isPrimal": false,
  "isGmax": false,
  "isRegional": false,
  "canGmax": false,
  "canDynamax": false,
  "canBeAlpha": false,
  "debutIn": "sv",
  "obtainableIn": ["sv-s", "sv-v", "lza"],
  "eventOnlyIn": [],
  "storableIn": ["home", "sv-s", "sv-v", "lza"],
  "shinyReleased": true,
  "baseHp": 48,
  "baseAtk": 35,
  "baseDef": 42,
  "baseSpAtk": 105,
  "baseSpDef": 60,
  "baseSpeed": 60,
  "height": 70,
  "weight": 800,
  "maleRate": 50,
  "femaleRate": 50,
  "baseForms": [],
  "forms": [],
  "refs": {
    "pkApiId": "969",
    "pkApiFormId": "969",
    "pkApiFormSlug": "glimmet",
    "smogon": "glimmet",
    "showdown": "glimmet",
    "showdownName": "Glimmet",
    "serebii": "glimmet",
    "bulbapedia": "Glimmet"
  },
  "names": {
    "eng": "Glimmet",
    "fra": "Germéclat",
    "deu": "Lumispross",
    "jap": "キラーメ",
    "kor": "초롱순",
    "chs": "晶光芽",
    "cht": "晶光芽"
  },
  "genus": {
    "eng": "Ore Pokémon",
    "fra": "Minerai",
    "deu": "Erz",
    "jap": "こうせきポケモン",
    "kor": "광석포켓몬",
    "chs": "矿石宝可梦",
    "cht": "礦石寶可夢"
  },
  "speciesNames": {},
  "formNames": {}
}
