{
  "id": "hoopa-unbound",
  "nid": "0720-unbound",
  "dexNum": 720,
  "formId": "unbound",
  "region": "kalos",
  "gen": 6,
  "type1": "psychic",
  "type2": "dark",
  "color": "purple",
  "ability1": "magician",
  "isPrerelease": false,
  "isDefault": false,
  "isForm": true,
  "isLegendary": false,
  "isMythical": true,
  "isBaby": false,
  "isUltraBeast": false,
  "isParadox": false,
  "paradoxSpecies": [],
  "isConvergent": false,
  "convergentSpecies": [],
  "isCosmeticForm": false,
  "isFemaleForm": false,
  "hasGenderDifferences": false,
  "isBattleOnlyForm": false,
  "isFusion": false,
  "isMega": false,
  "isPrimal": false,
  "isGmax": false,
  "isRegional": false,
  "canGmax": false,
  "canDynamax": true,
  "canBeAlpha": false,
  "debutIn": "oras",
  "obtainableIn": ["lza"],
  "eventOnlyIn": ["oras-or", "oras-as", "go"],
  "storableIn": ["oras-or", "oras-as", "go", "sm-s", "sm-m", "usum-us", "usum-um", "home", "sv-s", "sv-v"],
  "shinyReleased": false,
  "shinyLockedIn": ["lza"],
  "baseHp": 80,
  "baseAtk": 160,
  "baseDef": 60,
  "baseSpAtk": 170,
  "baseSpDef": 130,
  "baseSpeed": 80,
  "height": 650,
  "weight": 49000,
  "maleRate": 0,
  "femaleRate": 0,
  "baseSpecies": "hoopa",
  "baseForms": ["hoopa"],
  "forms": [],
  "refs": {
    "pkApiId": "10086",
    "pkApiFormId": "10188",
    "pkApiFormSlug": "hoopa-unbound",
    "smogon": "hoopa-unbound",
    "showdown": "hoopaunbound",
    "showdownName": "Hoopa-Unbound",
    "serebii": "hoopa",
    "bulbapedia": "Hoopa"
  },
  "names": {
    "eng": "Hoopa Unbound",
    "esp": "Hoopa Desatado",
    "fra": "Hoopa Déchaîné",
    "deu": "Entfesseltes Hoopa",
    "ita": "Hoopa Libero",
    "jap": "ときはなたれしフーパ",
    "kor": "굴레를 벗어난 후파",
    "chs": "解放胡帕",
    "cht": "解放胡帕"
  },
  "genus": {
    "eng": "Mischief Pokémon",
    "esp": "Pokémon Travesura",
    "fra": "Pokémon Chenapan",
    "deu": "Schabernack",
    "ita": "Pokémon Birba",
    "jap": "いたずらポケモン",
    "kor": "장난포켓몬",
    "chs": "顽童宝可梦",
    "cht": "頑童寶可夢"
  },
  "speciesNames": {
    "eng": "Hoopa",
    "fra": "Hoopa",
    "deu": "Hoopa",
    "jap": "フーパ",
    "kor": "후파",
    "chs": "胡帕",
    "cht": "胡帕"
  },
  "formNames": {
    "eng": "Hoopa Unbound",
    "esp": "Hoopa Desatado",
    "fra": "Hoopa Déchaîné",
    "deu": "Entfesseltes Hoopa",
    "ita": "Hoopa Libero",
    "jap": "ときはなたれしフーパ",
    "kor": "굴레를 벗어난 후파",
    "chs": "解放胡帕",
    "cht": "解放胡帕"
  }
}
