{
  "id": "jangmoo",
  "nid": "0782",
  "dexNum": 782,
  "region": "alola",
  "gen": 7,
  "type1": "dragon",
  "color": "gray",
  "ability1": "bulletproof",
  "ability2": "soundproof",
  "abilityHidden": "overcoat",
  "isPrerelease": false,
  "isDefault": true,
  "isForm": false,
  "isLegendary": false,
  "isMythical": false,
  "isBaby": false,
  "isUltraBeast": false,
  "isParadox": false,
  "paradoxSpecies": [],
  "isConvergent": false,
  "convergentSpecies": [],
  "isCosmeticForm": false,
  "isFemaleForm": false,
  "hasGenderDifferences": false,
  "isBattleOnlyForm": false,
  "isFusion": false,
  "isMega": false,
  "isPrimal": false,
  "isGmax": false,
  "isRegional": false,
  "canGmax": false,
  "canDynamax": true,
  "canBeAlpha": false,
  "debutIn": "sm",
  "obtainableIn": ["go", "sm-s", "sm-m", "usum-us", "usum-um", "swsh-sw", "swsh-sh", "sv-s", "sv-v"],
  "eventOnlyIn": [],
  "storableIn": ["go", "sm-s", "sm-m", "usum-us", "usum-um", "swsh-sw", "swsh-sh", "home", "sv-s", "sv-v"],
  "shinyReleased": true,
  "baseHp": 45,
  "baseAtk": 55,
  "baseDef": 65,
  "baseSpAtk": 45,
  "baseSpDef": 45,
  "baseSpeed": 45,
  "height": 60,
  "weight": 2970,
  "maleRate": 50,
  "femaleRate": 50,
  "baseForms": [],
  "forms": [],
  "refs": {
    "pkApiId": "782",
    "pkApiFormId": "782",
    "pkApiFormSlug": "jangmo-o",
    "smogon": "jangmoo",
    "showdown": "jangmoo",
    "showdownName": "Jangmo-o",
    "serebii": "jangmoo",
    "bulbapedia": "Jangmo-o"
  },
  "names": {
    "eng": "Jangmo-o",
    "fra": "Bébécaille",
    "deu": "Miniras",
    "jap": "ジャラコ",
    "kor": "짜랑꼬",
    "chs": "心鳞宝",
    "cht": "心鱗寶"
  },
  "genus": {
    "eng": "Scaly Pokémon",
    "esp": "Pokémon Escamas",
    "fra": "Pokémon Écailles",
    "deu": "Schuppentier-Pokémon",
    "ita": "Pokémon Squama",
    "jap": "うろこポケモン",
    "kor": "비늘포켓몬",
    "chs": "鳞片宝可梦",
    "cht": "鱗片寶可夢"
  },
  "speciesNames": {},
  "formNames": {}
}
