{
  "id": "lucario-mega-z",
  "nid": "0448-mega-z",
  "dexNum": 448,
  "formId": "mega-z",
  "region": "kalos",
  "gen": 9,
  "type1": "fighting",
  "type2": "steel",
  "color": "blue",
  "ability1": "steadfast",
  "ability2": "innerfocus",
  "abilityHidden": "justified",
  "isPrerelease": false,
  "isDefault": false,
  "isForm": true,
  "formItem": "lucarionitez",
  "isLegendary": false,
  "isMythical": false,
  "isBaby": false,
  "isUltraBeast": false,
  "isParadox": false,
  "paradoxSpecies": [],
  "isConvergent": false,
  "convergentSpecies": [],
  "isCosmeticForm": false,
  "isFemaleForm": false,
  "hasGenderDifferences": false,
  "isBattleOnlyForm": true,
  "isFusion": false,
  "isMega": true,
  "isPrimal": false,
  "isGmax": false,
  "isRegional": false,
  "canGmax": false,
  "canDynamax": false,
  "canBeAlpha": false,
  "debutIn": "lza",
  "obtainableIn": ["lza"],
  "eventOnlyIn": [],
  "storableIn": [],
  "shinyReleased": true,
  "baseHp": 70,
  "baseAtk": 100,
  "baseDef": 70,
  "baseSpAtk": 164,
  "baseSpDef": 70,
  "baseSpeed": 151,
  "height": 130,
  "weight": 4940,
  "maleRate": 87.5,
  "femaleRate": 12.5,
  "baseSpecies": "lucario",
  "baseForms": [],
  "forms": [],
  "refs": {
    "pkApiId": "448",
    "pkApiFormId": "448",
    "pkApiFormSlug": "lucario-mega-z",
    "smogon": "lucario-mega-z",
    "showdown": "lucariomegaz",
    "showdownName": "Lucario-Mega-Z",
    "serebii": "lucario",
    "bulbapedia": "Lucario"
  },
  "names": {
    "eng": "Mega Lucario Z",
    "esp": "Mega Lucario Z",
    "esla": "Mega Lucario Z",
    "fra": "MégaLucario Z",
    "deu": "Mega-Lucario Z",
    "ita": "Mega Lucario Z",
    "jap": "メガルカリオZ",
    "kor": "메가루카리오Z",
    "chs": "超级路卡利欧Z",
    "cht": "超級路卡利歐Z"
  },
  "genus": {
    "eng": "Aura Pokémon",
    "esp": "Pokémon Aura",
    "fra": "Pokémon Aura",
    "deu": "Aura-Pokémon",
    "ita": "Pokémon Aura",
    "jap": "はどうポケモン",
    "kor": "파동포켓몬",
    "chs": "波导宝可梦",
    "cht": "波導寶可夢"
  },
  "speciesNames": {
    "eng": "Lucario",
    "fra": "Lucario",
    "deu": "Lucario",
    "jap": "ルカリオ",
    "kor": "루카리오",
    "chs": "路卡利欧",
    "cht": "路卡利歐"
  },
  "formNames": {
    "eng": "Mega Form Z",
    "esp": "Forma Mega Z",
    "esla": "Forma Mega Z",
    "fra": "Méga-Forme Z",
    "deu": "Mega-Form Z",
    "ita": "Forma Mega Z",
    "jap": "メガZ",
    "kor": "메가Z",
    "chs": "超级Z",
    "cht": "超級Z"
  }
}
