{
  "id": "mudbray",
  "nid": "0749",
  "dexNum": 749,
  "region": "alola",
  "gen": 7,
  "type1": "ground",
  "color": "brown",
  "ability1": "owntempo",
  "ability2": "stamina",
  "abilityHidden": "innerfocus",
  "isPrerelease": false,
  "isDefault": true,
  "isForm": false,
  "isLegendary": false,
  "isMythical": false,
  "isBaby": false,
  "isUltraBeast": false,
  "isParadox": false,
  "paradoxSpecies": [],
  "isConvergent": false,
  "convergentSpecies": [],
  "isCosmeticForm": false,
  "isFemaleForm": false,
  "hasGenderDifferences": false,
  "isBattleOnlyForm": false,
  "isFusion": false,
  "isMega": false,
  "isPrimal": false,
  "isGmax": false,
  "isRegional": false,
  "canGmax": false,
  "canDynamax": true,
  "canBeAlpha": false,
  "debutIn": "sm",
  "obtainableIn": ["go", "sm-s", "sm-m", "usum-us", "usum-um", "swsh-sw", "swsh-sh", "sv-s", "sv-v"],
  "eventOnlyIn": [],
  "storableIn": ["go", "sm-s", "sm-m", "usum-us", "usum-um", "swsh-sw", "swsh-sh", "home", "sv-s", "sv-v"],
  "shinyReleased": true,
  "baseHp": 70,
  "baseAtk": 100,
  "baseDef": 70,
  "baseSpAtk": 45,
  "baseSpDef": 55,
  "baseSpeed": 45,
  "height": 100,
  "weight": 11000,
  "maleRate": 50,
  "femaleRate": 50,
  "baseForms": [],
  "forms": [],
  "refs": {
    "pkApiId": "749",
    "pkApiFormId": "749",
    "pkApiFormSlug": "mudbray",
    "smogon": "mudbray",
    "showdown": "mudbray",
    "showdownName": "Mudbray",
    "serebii": "mudbray",
    "bulbapedia": "Mudbray"
  },
  "names": {
    "eng": "Mudbray",
    "fra": "Tiboudet",
    "deu": "Pampuli",
    "jap": "ドロバンコ",
    "kor": "머드나기",
    "chs": "泥驴仔",
    "cht": "泥驢仔"
  },
  "genus": {
    "eng": "Donkey Pokémon",
    "esp": "Pokémon Asno",
    "fra": "Pokémon Âne",
    "deu": "Packesel-Pokémon",
    "ita": "Pokémon Ciuconiglio",
    "jap": "うさぎうまポケモン",
    "kor": "당나귀포켓몬",
    "chs": "驴宝可梦",
    "cht": "驢寶可夢"
  },
  "speciesNames": {},
  "formNames": {}
}
