{
  "id": "spinda",
  "nid": "0327",
  "dexNum": 327,
  "region": "hoenn",
  "gen": 3,
  "type1": "normal",
  "color": "brown",
  "ability1": "owntempo",
  "ability2": "tangledfeet",
  "abilityHidden": "contrary",
  "isPrerelease": false,
  "isDefault": true,
  "isForm": false,
  "isLegendary": false,
  "isMythical": false,
  "isBaby": false,
  "isUltraBeast": false,
  "isParadox": false,
  "paradoxSpecies": [],
  "isConvergent": false,
  "convergentSpecies": [],
  "isCosmeticForm": false,
  "isFemaleForm": false,
  "hasGenderDifferences": false,
  "isBattleOnlyForm": false,
  "isFusion": false,
  "isMega": false,
  "isPrimal": false,
  "isGmax": false,
  "isRegional": false,
  "canGmax": false,
  "canDynamax": true,
  "canBeAlpha": false,
  "debutIn": "rs",
  "obtainableIn": [
    "rs-r",
    "rs-s",
    "e",
    "xy-x",
    "xy-y",
    "oras-or",
    "oras-as",
    "go",
    "sm-s",
    "sm-m",
    "usum-us",
    "usum-um",
    "bdsp-bd",
    "bdsp-sp"
  ],
  "eventOnlyIn": [],
  "storableIn": [
    "rs-r",
    "rs-s",
    "frlg-fr",
    "frlg-lg",
    "e",
    "dp-d",
    "dp-p",
    "pt",
    "hgss-hg",
    "hgss-ss",
    "bw-b",
    "bw-w",
    "b2w2-b2",
    "b2w2-w2",
    "xy-x",
    "xy-y",
    "oras-or",
    "oras-as",
    "go",
    "sm-s",
    "sm-m",
    "usum-us",
    "usum-um",
    "home",
    "bdsp-bd",
    "bdsp-sp"
  ],
  "shinyReleased": true,
  "baseHp": 60,
  "baseAtk": 60,
  "baseDef": 60,
  "baseSpAtk": 60,
  "baseSpDef": 60,
  "baseSpeed": 60,
  "height": 110,
  "weight": 500,
  "maleRate": 50,
  "femaleRate": 50,
  "baseForms": [],
  "forms": [],
  "refs": {
    "pkApiId": "327",
    "pkApiFormId": "327",
    "pkApiFormSlug": "spinda",
    "smogon": "spinda",
    "showdown": "spinda",
    "showdownName": "Spinda",
    "serebii": "spinda",
    "bulbapedia": "Spinda"
  },
  "names": {
    "eng": "Spinda",
    "fra": "Spinda",
    "deu": "Pandir",
    "jap": "パッチール",
    "kor": "얼루기",
    "chs": "晃晃斑",
    "cht": "晃晃斑"
  },
  "genus": {
    "eng": "Spot Panda Pokémon",
    "esp": "Pokémon Panda Topos",
    "fra": "Pokémon Panda Tache",
    "deu": "Punkt-Panda",
    "ita": "Pokémon Macchipanda",
    "jap": "ぶちパンダポケモン",
    "kor": "얼룩팬더포켓몬",
    "chs": "斑点熊猫宝可梦",
    "cht": "斑點熊貓寶可夢"
  },
  "speciesNames": {},
  "formNames": {}
}
