{
  "id": "unfezant-f",
  "nid": "0521-f",
  "dexNum": 521,
  "formId": "f",
  "region": "unova",
  "gen": 5,
  "type1": "normal",
  "type2": "flying",
  "color": "gray",
  "ability1": "bigpecks",
  "ability2": "superluck",
  "abilityHidden": "rivalry",
  "isPrerelease": false,
  "isDefault": false,
  "isForm": true,
  "isLegendary": false,
  "isMythical": false,
  "isBaby": false,
  "isUltraBeast": false,
  "isParadox": false,
  "paradoxSpecies": [],
  "isConvergent": false,
  "convergentSpecies": [],
  "isCosmeticForm": true,
  "isFemaleForm": true,
  "hasGenderDifferences": true,
  "isBattleOnlyForm": false,
  "isFusion": false,
  "isMega": false,
  "isPrimal": false,
  "isGmax": false,
  "isRegional": false,
  "canGmax": false,
  "canDynamax": true,
  "canBeAlpha": false,
  "debutIn": "bw",
  "obtainableIn": ["bw-b", "bw-w", "b2w2-b2", "b2w2-w2", "go", "swsh-sw", "swsh-sh"],
  "eventOnlyIn": [],
  "storableIn": [
    "bw-b",
    "bw-w",
    "b2w2-b2",
    "b2w2-w2",
    "xy-x",
    "xy-y",
    "oras-or",
    "oras-as",
    "go",
    "sm-s",
    "sm-m",
    "usum-us",
    "usum-um",
    "swsh-sw",
    "swsh-sh",
    "home"
  ],
  "shinyReleased": true,
  "baseHp": 80,
  "baseAtk": 115,
  "baseDef": 80,
  "baseSpAtk": 65,
  "baseSpDef": 55,
  "baseSpeed": 93,
  "height": 120,
  "weight": 2900,
  "maleRate": 50,
  "femaleRate": 50,
  "baseSpecies": "unfezant",
  "baseForms": [],
  "forms": [],
  "refs": {
    "pkApiId": "521",
    "pkApiFormId": "521",
    "pkApiFormSlug": "unfezant",
    "smogon": "unfezant",
    "showdown": "unfezant",
    "showdownName": "Unfezant",
    "serebii": "unfezant",
    "bulbapedia": "Unfezant"
  },
  "evolvesFrom": "tranquill",
  "evoFromLevel": 32,
  "names": {
    "eng": "Unfezant (Female)",
    "fra": "Déflaisan (Female)",
    "deu": "Fasasnob (Female)"
  },
  "genus": {
    "eng": "Proud Pokémon",
    "esp": "Pokémon Altanero",
    "fra": "Pokémon Fier",
    "deu": "Stolz-Pokémon",
    "ita": "Pokémon Orgoglio",
    "jap": "プライドポケモン",
    "kor": "프라이드포켓몬",
    "chs": "自尊心宝可梦",
    "cht": "自尊心寶可夢"
  },
  "speciesNames": {
    "eng": "Unfezant",
    "fra": "Déflaisan",
    "deu": "Fasasnob",
    "jap": "ケンホロウ",
    "kor": "켄호로우",
    "chs": "高傲雉鸡",
    "cht": "高傲雉雞"
  },
  "formNames": {
    "eng": "Female",
    "esp": "Hembra",
    "esla": "Hembra",
    "fra": "Femelle",
    "deu": "Weiblich",
    "ita": "Femmina",
    "jap": "メス",
    "kor": "암컷",
    "chs": "雌性",
    "cht": "雌性"
  }
}
