{
  "id": "victreebel",
  "nid": "0071",
  "dexNum": 71,
  "region": "kanto",
  "gen": 1,
  "type1": "grass",
  "type2": "poison",
  "color": "green",
  "ability1": "chlorophyll",
  "abilityHidden": "gluttony",
  "isPrerelease": false,
  "isDefault": true,
  "isForm": false,
  "isLegendary": false,
  "isMythical": false,
  "isBaby": false,
  "isUltraBeast": false,
  "isParadox": false,
  "paradoxSpecies": [],
  "isConvergent": false,
  "convergentSpecies": [],
  "isCosmeticForm": false,
  "isFemaleForm": false,
  "hasGenderDifferences": false,
  "isBattleOnlyForm": false,
  "isFusion": false,
  "isMega": false,
  "isPrimal": false,
  "isGmax": false,
  "isRegional": false,
  "canGmax": false,
  "canDynamax": true,
  "canBeAlpha": false,
  "debutIn": "rb",
  "obtainableIn": [
    "rb-r",
    "rb-b",
    "y",
    "gs-g",
    "gs-s",
    "c",
    "frlg-fr",
    "frlg-lg",
    "xd",
    "hgss-hg",
    "hgss-ss",
    "xy-x",
    "xy-y",
    "go",
    "lgpe-lgp",
    "lgpe-lge",
    "bdsp-bd",
    "bdsp-sp",
    "sv-s",
    "sv-v",
    "lza"
  ],
  "eventOnlyIn": [],
  "storableIn": [
    "rb-r",
    "rb-b",
    "y",
    "gs-g",
    "gs-s",
    "c",
    "rs-r",
    "rs-s",
    "frlg-fr",
    "frlg-lg",
    "e",
    "dp-d",
    "dp-p",
    "pt",
    "hgss-hg",
    "hgss-ss",
    "bw-b",
    "bw-w",
    "b2w2-b2",
    "b2w2-w2",
    "xy-x",
    "xy-y",
    "oras-or",
    "oras-as",
    "go",
    "sm-s",
    "sm-m",
    "usum-us",
    "usum-um",
    "lgpe-lgp",
    "lgpe-lge",
    "home",
    "bdsp-bd",
    "bdsp-sp",
    "sv-s",
    "sv-v"
  ],
  "shinyReleased": true,
  "baseHp": 80,
  "baseAtk": 105,
  "baseDef": 65,
  "baseSpAtk": 100,
  "baseSpDef": 70,
  "baseSpeed": 70,
  "height": 170,
  "weight": 1550,
  "maleRate": 50,
  "femaleRate": 50,
  "baseForms": [],
  "forms": ["victreebel-mega"],
  "refs": {
    "pkApiId": "71",
    "pkApiFormId": "71",
    "pkApiFormSlug": "victreebel",
    "smogon": "victreebel",
    "showdown": "victreebel",
    "showdownName": "Victreebel",
    "serebii": "victreebel",
    "bulbapedia": "Victreebel"
  },
  "evolvesFrom": "weepinbell",
  "evoFromItem": "leafstone",
  "names": {
    "eng": "Victreebel",
    "fra": "Empiflor",
    "deu": "Sarzenia",
    "jap": "ウツボット",
    "kor": "우츠보트",
    "chs": "大食花",
    "cht": "大食花"
  },
  "genus": {
    "eng": "Flycatcher Pokémon",
    "esp": "Pokémon Matamoscas",
    "fra": "Pokémon Carnivore",
    "deu": "Fliegentod",
    "ita": "Pokémon Moschivoro",
    "jap": "ハエとりポケモン",
    "kor": "파리잡이포켓몬",
    "chs": "捕蝇宝可梦",
    "cht": "捕蠅寶可夢"
  },
  "speciesNames": {},
  "formNames": {}
}
