{
  "id": "xerneas-active",
  "nid": "0716-active",
  "dexNum": 716,
  "formId": "active",
  "region": "kalos",
  "gen": 6,
  "type1": "fairy",
  "color": "blue",
  "ability1": "fairyaura",
  "isPrerelease": false,
  "isDefault": false,
  "isForm": true,
  "isLegendary": true,
  "isMythical": false,
  "isBaby": false,
  "isUltraBeast": false,
  "isParadox": false,
  "paradoxSpecies": [],
  "isConvergent": false,
  "convergentSpecies": [],
  "isCosmeticForm": false,
  "isFemaleForm": false,
  "hasGenderDifferences": false,
  "isBattleOnlyForm": true,
  "isFusion": false,
  "isMega": false,
  "isPrimal": false,
  "isGmax": false,
  "isRegional": false,
  "canGmax": false,
  "canDynamax": true,
  "canBeAlpha": false,
  "debutIn": "xy",
  "obtainableIn": ["xy-x", "xy-y", "go", "swsh-sw", "swsh-sh", "lza"],
  "eventOnlyIn": [],
  "storableIn": [],
  "shinyReleased": true,
  "shinyLockedIn": ["xy-x", "xy-y", "lza"],
  "baseHp": 126,
  "baseAtk": 131,
  "baseDef": 95,
  "baseSpAtk": 131,
  "baseSpDef": 98,
  "baseSpeed": 99,
  "height": 300,
  "weight": 21500,
  "maleRate": 0,
  "femaleRate": 0,
  "baseSpecies": "xerneas",
  "baseForms": ["xerneas"],
  "forms": [],
  "refs": {
    "pkApiId": "716",
    "pkApiFormId": "716",
    "pkApiFormSlug": "xerneas-active",
    "smogon": "xerneas-active",
    "showdown": "xerneas",
    "showdownName": "Xerneas",
    "serebii": "xerneas",
    "bulbapedia": "Xerneas"
  },
  "names": {
    "eng": "Xerneas (Active Mode)",
    "fra": "Xerneas (Mode Déchaîné)",
    "deu": "Xerneas (Aktiv-Modus)"
  },
  "genus": {},
  "speciesNames": {
    "eng": "Xerneas",
    "fra": "Xerneas",
    "deu": "Xerneas"
  },
  "formNames": {
    "eng": "Active Mode",
    "esp": "Modo Activo",
    "fra": "Mode Déchaîné",
    "deu": "Aktiv-Modus",
    "ita": "Modo Attivo",
    "jap": "アクティブモード",
    "kor": "액티브모드",
    "chs": "活跃模式",
    "cht": "活躍模式"
  }
}
